[
  {
    "id": "1",
    "id_serie": "2",
    "Link": "https://itunes.apple.com/de/podcast/2-gregor/id1150800298?i=1000375725662&mt=2",
    "pod_link": "https://pod.link/1150800298/episode/8b7168798ebf8d2e3a8d6f6aef9154ad",
    "direkt_Link": "https://traffic.megaphone.fm/GLT1741636493.mp3?updated=1474689332",
    "Titel": "#2 Gregor",
    "Dauer": "48",
    "Kommentar": "20 years ago, Gregor lent some CDs to a musician friend. The CDs helped make him a famous rockstar. Now, Gregor would like some recognition. But mostly, he wants his CDs back."
  },
  {
    "id": "2",
    "id_serie": "5",
    "Link": "https://itunes.apple.com/de/podcast/105-at-worlds-end/id941907967?i=1000392529567&mt=2",
    "pod_link": "https://pod.link/941907967/episode/cb735f1b95228a46dda6696718a9d248",
    "direkt_Link": "https://traffic.megaphone.fm/GLT2587587615.mp3?updated=1505975085",
    "Titel": "#105 At World's End",
    "Dauer": "36",
    "Kommentar": "Phia helps a listener track down a mythical, vanished video game. "
  },
  {
    "id": "3",
    "id_serie": "8",
    "Link": "https://itunes.apple.com/de/podcast/when-everything-clicks/id1028908750?i=1000413027878&mt=2",
    "pod_link": "https://pod.link/1028908750/episode/8c7cab36588394087b5760779632b9a6",
    "direkt_Link": "https://play.podtrac.com/npr-510308/npr.mc.tritondigital.com/NPR_510308/media/anon.npr-podcasts/podcast/npr/hiddenbrain/2018/06/20180604_hiddenbrain_hb_clicker_training_-_final_podcast_mix-1667ed29-bf49-4a59-85cd-f199e24709a6.mp3?orgId=1&d=3092&p=510308&story=616829753&t=podcast&e=616829753&ft=pod&f=510308",
    "Titel": "When Everything Clicks",
    "Dauer": "51",
    "Kommentar": "There can be a lot of psychological noise involved in teaching. But what if we replaced all that mental chit chat....with a click?"
  },
  {
    "id": "4",
    "id_serie": "9",
    "Link": "https://itunes.apple.com/de/podcast/toleranz-und-recht-von-rainer-forst/id828868503?i=1000413979292&mt=2",
    "pod_link": "https://podcast-mp3.dradio.de/podcast/2018/06/17/deutschlandfunknova_toleranz_und_recht_von_20180617_698e57cd.mp3",
    "direkt_Link": "https://podcast-mp3.dradio.de/podcast/2018/06/17/deutschlandfunknova_toleranz_und_recht_von_20180617_698e57cd.mp3",
    "Titel": "Toleranz und Recht von Rainer Forst",
    "Dauer": "45",
    "Kommentar": "Den einen gilt Toleranz als Form von Respekt und erstrebenswerter Tugend, den anderen als Gleichg\u00fcltigkeit oder Schw\u00e4che. Der Philosoph Rainer Forst erkl\u00e4rt in seinem Vortrag die unterschiedlichen Formen der Toleranz und geht dabei auch auf aktuelle Beispiele wie das Kruzifix-Gesetz in Bayern ein."
  },
  {
    "id": "5",
    "id_serie": "10",
    "Link": "https://itunes.apple.com/de/podcast/klaas-heufer-umlauf-warum-machst-du-das-was-du-machst/id1168045239?i=1000409805239&mt=2",
    "pod_link": "https://pod.link/1168045239/episode/a0d743e62bf2adf838c3dc9b403065a1",
    "direkt_Link": "http://feeds.soundcloud.com/stream/434927496-hotelmatze-klaas-heufer-umlauf-warum-machst-du-das-was-du-machst.mp3",
    "Titel": "Klaas Heufer-Umlauf \u2013 Warum machst du das, was du machst?",
    "Dauer": "77",
    "Kommentar": "Klaas halt"
  },
  {
    "id": "6",
    "id_serie": "11",
    "Link": "https://itunes.apple.com/de/podcast/episode-273-zoe-chace/id551088534?i=1000396551394&mt=2",
    "pod_link": "https://pod.link/551088534/episode/483f303ecd4f162a81888636a197a1c9",
    "direkt_Link": "https://audio.simplecast.com/410a8316.mp3",
    "Titel": "Episode 273: Zoe Chace",
    "Dauer": "65",
    "Kommentar": "Zoe Chace is a reporter and producer at This American Life. \u201cRadio is a movie in your head...\""
  },
  {
    "id": "7",
    "id_serie": "14",
    "Link": "https://itunes.apple.com/de/podcast/christopher-nolan/id342735925?i=1000402821594&mt=2",
    "pod_link": "https://pod.link/342735925/episode/998767c14465880538f4f03fe81a193a",
    "direkt_Link": "http://open.live.bbc.co.uk/mediaselector/5/redir/version/2.0/mediaset/audio-nondrm-download/proto/http/vpid/p05y86ry.mp3",
    "Titel": "Christopher Nolan",
    "Dauer": "36",
    "Kommentar": "Christopher Nolan is best known for reviving the Batman film franchise and for directing the blockbusters Inception and Dunkirk."
  },
  {
    "id": "8",
    "id_serie": "15",
    "Link": "https://www.swr.de/swr2/programm/sendungen/wissen/sex-mit-maschinen-revolutionieren-roboter-das-liebesleben/-/id=660374/did=19859746/nid=660374/1n4t0pj/index.html",
    "pod_link": "http://avdlswr-a.akamaihd.net/swr/swr2/wissen/sendungen/2017/07/swr2wissen-20170719-sex-mit-maschinen.m.mp3",
    "direkt_Link": "http://avdlswr-a.akamaihd.net/swr/swr2/wissen/sendungen/2017/07/swr2wissen-20170719-sex-mit-maschinen.m.mp3",
    "Titel": "Sex mit Maschinen",
    "Dauer": "28",
    "Kommentar": "\"Touch me\", \"Fass mich an\", Sexroboter sind deutlich. Allerdings sind sie kein Ersatz f\u00fcr echte Kommunikation und Beziehung. Sie sind nur Maschinen."
  },
  {
    "id": "9",
    "id_serie": "19",
    "Link": "https://www.wnyc.org/story/james-taylor-will-teach-you-guitar-pod/",
    "pod_link": "https://www.podtrac.com/pts/redirect.mp3/audio.wnyc.org/tnyradiohour/tnyradiohour070717a.mp3",
    "direkt_Link": "https://www.podtrac.com/pts/redirect.mp3/audio.wnyc.org/tnyradiohour/tnyradiohour070717a.mp3",
    "Titel": "James Taylor Will Teach You Guitar",
    "Dauer": "37",
    "Kommentar": "James Taylor\u2019s songs are so familiar that they seem to have always existed. On stage at the New Yorker Festival in 2010, Taylor peeled back some of his influences: the Beatles, Bach, show tunes, and Antonio Carlos Jobim. Taylor played a few of his hits and gave staff writer Adam Gopnik a quick lesson."
  },
  {
    "id": "10",
    "id_serie": "20",
    "Link": "https://itunes.apple.com/de/podcast/arcade-fire-put-your-money-on-me/id788236947?i=1000409832341&mt=2",
    "pod_link": "https://pod.link/788236947/episode/cb98e6dea3dea928d54d10abf4a5aaf3",
    "direkt_Link": "https://dts.podtrac.com/redirect.mp3/dovetail.prxu.org/song-exploder/9b1e450e-bc1f-4f18-88c6-b504b8906eeb/SongExploder134_ArcadeFire_DT.mp3",
    "Titel": "Arcade Fire - Put Your Money On Me",
    "Dauer": "21",
    "Kommentar": "Arcade Fire is a Grammy-winning six-piece band originally from Montreal. They\u2019ve released five albums, and the last three have all debuted at number one on the charts..."
  },
  {
    "id": "13",
    "id_serie": "24",
    "Link": null,
    "pod_link": "https://pod.link/1076398666/episode/6257f50e4ae32f0e64838edcfd66c39a",
    "direkt_Link": null,
    "Titel": "\"Antje Boesler, wie oft h\u00f6rst du den Satz: Schei\u00df Busfahrerin?\"",
    "Dauer": "30",
    "Kommentar": "Seit 32 Jahren f\u00e4hrt Antje Boesler als Busfahrerin durch Berlin. Meckernde Fahrg\u00e4ste, Polizeieins\u00e4tze oder Hungrige, die in ihrem Bus einen D\u00f6ner essen wollen, geh\u00f6ren zu ihrem Berufsalltag. Wenn sie mal wieder gefragt wird, warum der Bus schon wieder zu sp\u00e4t oder ausgefallen ist, hat sie gute Erkl\u00e4rungen parat."
  },
  {
    "id": "12",
    "id_serie": "0",
    "Link": null,
    "pod_link": "",
    "direkt_Link": null,
    "Titel": "",
    "Dauer": "0",
    "Kommentar": ""
  }
]
